{"textures":{"0":"modelengine:entity/kriger","1":"modelengine:entity/kriger_parts","2":"modelengine:entity/kriger_damaged"},"elements":[{"name":"cube","from":[6.2,6.1796784,5.718568],"to":[9.8,7.9796786,8.718568],"rotation":{"angle":0.0,"axis":"x","origin":[7.85,15.029679,8.268568]},"faces":{"down":{"uv":[8.0,7.5,8.75,8.125],"rotation":0,"texture":"#2","tintindex":0},"east":{"uv":[10.125,3.625,9.5,4.0],"rotation":0,"texture":"#2","tintindex":0},"north":{"uv":[9.5,8.0,8.75,8.375],"rotation":0,"texture":"#2","tintindex":0},"south":{"uv":[9.5,8.375,8.75,8.75],"rotation":0,"texture":"#2","tintindex":0},"up":{"uv":[6.375,8.625,7.125,8.0],"rotation":0,"texture":"#2","tintindex":0},"west":{"uv":[10.0,8.75,9.375,9.125],"rotation":0,"texture":"#2","tintindex":0}}},{"name":"cube","from":[6.14,7.156886,3.6185677],"to":[9.860001,8.956886,5.4185677],"rotation":{"angle":-45.0,"axis":"x","origin":[8.3,7.4568863,4.518568]},"faces":{"down":{"uv":[8.875,6.0,9.625,6.375],"rotation":0,"texture":"#2","tintindex":0},"east":{"uv":[10.125,4.375,9.75,4.75],"rotation":0,"texture":"#2","tintindex":0},"north":{"uv":[9.375,8.75,8.625,9.125],"rotation":0,"texture":"#2","tintindex":0},"south":{"uv":[9.625,2.625,8.875,3.0],"rotation":0,"texture":"#2","tintindex":0},"up":{"uv":[8.875,3.375,9.625,3.0],"rotation":0,"texture":"#2","tintindex":0},"west":{"uv":[3.125,9.75,2.75,10.125],"rotation":0,"texture":"#2","tintindex":0}}},{"name":"cube","from":[6.2,6.8,4.3999996],"to":[9.8,8.6,6.2],"rotation":{"angle":22.5,"axis":"x","origin":[8.3,7.7,4.3999996]},"faces":{"down":{"uv":[9.125,0.5,9.875,0.875],"rotation":0,"texture":"#2","tintindex":0},"east":{"uv":[5.375,9.75,5.0,10.125],"rotation":0,"texture":"#2","tintindex":0},"north":{"uv":[9.75,2.0,9.0,2.375],"rotation":0,"texture":"#2","tintindex":0},"south":{"uv":[9.75,4.375,9.0,4.75],"rotation":0,"texture":"#2","tintindex":0},"up":{"uv":[9.0,5.125,9.75,4.75],"rotation":0,"texture":"#2","tintindex":0},"west":{"uv":[10.125,4.75,9.75,5.125],"rotation":0,"texture":"#2","tintindex":0}}}],"display":{"head":{"translation":[0.0,-6.4,0.0],"rotation":[0.0,0.0,0.0],"scale":[3.8095,3.8095,3.8095]}}}